r2x_sienna/__init__.py
r2x_sienna/config.py
r2x_sienna/exporter.py
r2x_sienna/logger.py
r2x_sienna/models/__init__.py
r2x_sienna/models/attributes.py
r2x_sienna/models/base.py
r2x_sienna/models/branch.py
r2x_sienna/models/core.py
r2x_sienna/models/costs.py
r2x_sienna/models/enums.py
r2x_sienna/models/generators.py
r2x_sienna/models/getters.py
r2x_sienna/models/load.py
r2x_sienna/models/named_tuples.py
r2x_sienna/models/py.typed
r2x_sienna/models/services.py
r2x_sienna/models/topology.py
r2x_sienna/parser.py
r2x_sienna/plugin.py
r2x_sienna/py.pyted
r2x_sienna/serialization.py
r2x_sienna/units.py
r2x_sienna/upgrader/__init__.py
r2x_sienna/upgrader/data_upgrader.py
r2x_sienna/upgrader/upgrade_steps.py
r2x_sienna-0.1.0.dist-info/WHEEL
r2x_sienna-0.1.0.dist-info/entry_points.txt
r2x_sienna-0.1.0.dist-info/METADATA
r2x_sienna-0.1.0.dist-info/RECORD
