Metadata-Version: 2.3
Name: r2x-sienna
Version: 0.1.0
Summary: Sienna model plugin
Keywords: Sienna
Author: mcllerena, pesap
Author-email: mcllerena <mcllerena@users.noreply.github.com>, pesap <pesap@users.noreply.github.com>
License: BSD 3-Clause License
Classifier: Development Status :: 4 - Beta
Classifier: Intended Audience :: Developers
Classifier: Intended Audience :: Science/Research
Classifier: License :: OSI Approved :: BSD License
Classifier: Topic :: Software Development :: Build Tools
Classifier: Programming Language :: Python
Classifier: Programming Language :: Python :: 3
Classifier: Programming Language :: Python :: 3 :: Only
Classifier: Programming Language :: Python :: 3.11
Classifier: Programming Language :: Python :: 3.12
Classifier: Programming Language :: Python :: 3.13
Classifier: License :: OSI Approved :: BSD License
Classifier: Natural Language :: English
Classifier: Operating System :: OS Independent
Classifier: Topic :: File Formats :: JSON
Classifier: Topic :: Scientific/Engineering
Classifier: Topic :: Scientific/Engineering :: Information Analysis
Classifier: Topic :: Scientific/Engineering :: Interface Engine/Protocol Translator
Classifier: Topic :: Software Development :: Build Tools
Classifier: Topic :: Software Development :: Libraries :: Python Modules
Classifier: Typing :: Typed
Requires-Dist: r2x-core>=0.1.1,<1.0.0
Maintainer: mcllerena, pesap
Maintainer-email: mcllerena <mcllerena@users.noreply.github.com>, pesap <pesap@users.noreply.github.com>
Requires-Python: >=3.11, <3.14
